girder_plugin_worker/__init__.py
girder_plugin_worker/constants.py
girder_plugin_worker/event_handlers.py
girder_plugin_worker/status.py
girder_plugin_worker/utils.py
girder_plugin_worker/api/__init__.py
girder_plugin_worker/api/worker.py
girder_plugin_worker/web_client/dist/girder-plugin-worker.umd.cjs
girder_plugin_worker/web_client/dist/style.css
girder_plugin_worker-5.0.0a14.dev27.dist-info/METADATA
girder_plugin_worker-5.0.0a14.dev27.dist-info/WHEEL
girder_plugin_worker-5.0.0a14.dev27.dist-info/entry_points.txt
girder_plugin_worker-5.0.0a14.dev27.dist-info/top_level.txt
girder_plugin_worker-5.0.0a14.dev27.dist-info/RECORD
